{
  "name": "Marilyn Sanders",
  "title": "Account Manager",
  "affiliate": "content/affiliates/construction.json",
  "photo": "",
  "bio": "As Account Manager at Birdsey Group, Marilyn Sanders supports client communication, project coordination, and day-to-day account management across construction-related engagements. Her work helps maintain clear expectations, responsive communication, and steady project support.\n\nMarilyn’s role reinforces the Birdsey Standard through transparency, accountability, and client-focused execution.\n",
  "linkedinUrl": "https://www.linkedin.com/in/sandersmarilyn/",
  "miniBioEnabled": false,
  "profilePageEnabled": true,
  "order": 8
}